huaweicloudsdkmapds/__init__.py
huaweicloudsdkmapds/v1/__init__.py
huaweicloudsdkmapds/v1/mapds_async_client.py
huaweicloudsdkmapds/v1/mapds_client.py
huaweicloudsdkmapds/v1/model/__init__.py
huaweicloudsdkmapds/v1/model/create_credential_request.py
huaweicloudsdkmapds/v1/model/create_credential_request_body.py
huaweicloudsdkmapds/v1/model/create_credential_request_body_credential.py
huaweicloudsdkmapds/v1/model/create_credential_response.py
huaweicloudsdkmapds/v1/model/create_sas_token_request.py
huaweicloudsdkmapds/v1/model/create_sas_token_request_body.py
huaweicloudsdkmapds/v1/model/create_sas_token_response.py
huaweicloudsdkmapds/v1/model/credentials_resp_credentials.py
huaweicloudsdkmapds/v1/model/delete_cedential_request.py
huaweicloudsdkmapds/v1/model/delete_cedential_response.py
huaweicloudsdkmapds/v1/model/show_credential_request.py
huaweicloudsdkmapds/v1/model/show_credential_response.py
huaweicloudsdkmapds/v1/model/show_map_tile_request.py
huaweicloudsdkmapds/v1/model/show_map_tile_response.py
huaweicloudsdkmapds/v1/region/__init__.py
huaweicloudsdkmapds/v1/region/mapds_region.py
huaweicloudsdkmapds-3.1.184.dist-info/METADATA
huaweicloudsdkmapds-3.1.184.dist-info/WHEEL
huaweicloudsdkmapds-3.1.184.dist-info/licenses/LICENSE
huaweicloudsdkmapds-3.1.184.dist-info/RECORD
